EmoPy/__init__.py
EmoPy/examples/__init__.py
EmoPy/examples/convolutional_lstm_model.py
EmoPy/examples/convolutional_model.py
EmoPy/examples/fermodel_example.py
EmoPy/examples/timedelay_conv_model.py
EmoPy/examples/transferlearning_model.py
EmoPy/examples/image_data/sample.csv
EmoPy/examples/image_data/sample_anger_image2.png
EmoPy/examples/image_data/sample_disgust_image.png
EmoPy/examples/image_data/sample_happy_image.png
EmoPy/examples/image_data/sample_image_directory/anger/S074_004_00000010.png
EmoPy/examples/image_data/sample_image_directory/anger/S074_004_00000018.png
EmoPy/examples/image_data/sample_image_directory/anger/S113_008_00000016.png
EmoPy/examples/image_data/sample_image_directory/anger/S113_008_00000019.png
EmoPy/examples/image_data/sample_image_directory/anger/S125_008_00000009.png
EmoPy/examples/image_data/sample_image_directory/anger/S125_008_00000010.png
EmoPy/examples/image_data/sample_image_directory/happiness/S052_004_00000022.png
EmoPy/examples/image_data/sample_image_directory/happiness/S052_004_00000033.png
EmoPy/examples/image_data/sample_image_directory/happiness/S055_005_00000030.png
EmoPy/examples/image_data/sample_image_directory/happiness/S055_005_00000043.png
EmoPy/examples/image_data/sample_image_directory/happiness/S074_005_00000034.png
EmoPy/examples/image_data/sample_image_directory/happiness/S074_005_00000043.png
EmoPy/examples/image_data/sample_image_directory/surprise/S052_001_00000010.png
EmoPy/examples/image_data/sample_image_directory/surprise/S052_001_00000015.png
EmoPy/examples/image_data/sample_image_directory/surprise/S055_001_00000007.png
EmoPy/examples/image_data/sample_image_directory/surprise/S055_001_00000009.png
EmoPy/examples/image_data/sample_image_directory/surprise/S074_002_00000010.png
EmoPy/examples/image_data/sample_image_directory/surprise/S074_002_00000016.png
EmoPy/examples/image_data/sample_image_series_directory/anger/S055_004/S055_004_00000001.png
EmoPy-0.0.5.dist-info/LICENSE
EmoPy-0.0.5.dist-info/METADATA
EmoPy-0.0.5.dist-info/WHEEL
EmoPy-0.0.5.dist-info/top_level.txt
EmoPy-0.0.5.dist-info/RECORD
