Metadata-Version: 2.1
Name: EmoPy
Version: 0.0.5
Summary: A deep neural net toolkit for emotion analysis via Facial Expression Recognition (FER)
Home-page: https://github.com/thoughtworksarts/EmoPy
Author: ThoughtWorks Arts
Author-email: info@thoughtworksarts.io
License: UNKNOWN
Platform: UNKNOWN
Classifier: Programming Language :: Python :: 3.6
Classifier: Operating System :: MacOS :: MacOS X
Requires-Python: >=3.6.3,<3.7
Requires-Dist: keras (>=2.2.0)
Requires-Dist: lasagne
Requires-Dist: pytest
Requires-Dist: matplotlib (>2.1.0)
Requires-Dist: numpy (<=1.14.5,>=1.13.3)
Requires-Dist: scikit-image (>=0.13.1)
Requires-Dist: scikit-learn (>=0.19.1)
Requires-Dist: scikit-neuralnetwork (>=0.7)
Requires-Dist: scipy (>=0.19.1)
Requires-Dist: tensorflow (>=1.10.1)
Requires-Dist: opencv-python
Requires-Dist: h5py
Requires-Dist: pydot
Requires-Dist: graphviz
